chr2png.py
png2chr.py
png2chr-0.1.0.dist-info/DESCRIPTION.rst
png2chr-0.1.0.dist-info/METADATA
png2chr-0.1.0.dist-info/RECORD
png2chr-0.1.0.dist-info/WHEEL
png2chr-0.1.0.dist-info/entry_points.txt
png2chr-0.1.0.dist-info/metadata.json
png2chr-0.1.0.dist-info/top_level.txt
