Metadata-Version: 2.0
Name: png2chr
Version: 0.1.0
Summary: Simple two-file library to convert between a 4-index PNG file and NES CHR file
Home-page: https://github.com/Taywee/png2chr
Author: Taylor C. Richberger <taywee@gmx.com>
Author-email: taywee@gmx.com
License: GPL3
Platform: UNKNOWN
Classifier: Intended Audience :: Developers
Classifier: License :: OSI Approved :: GNU General Public License v3 or later (GPLv3+)
Classifier: Natural Language :: English
Classifier: Programming Language :: Python :: 3
Classifier: Programming Language :: Python :: 3.5
Classifier: Programming Language :: Python :: Implementation :: CPython
Classifier: Topic :: Software Development :: Embedded Systems
Requires-Dist: pypng
